lsyiot_qweather_sdk/__init__.py
lsyiot_qweather_sdk/api.py
lsyiot_qweather_sdk/exceptions.py
lsyiot_qweather_sdk-1.0.1.dist-info/licenses/LICENSE
lsyiot_qweather_sdk-1.0.1.dist-info/METADATA
lsyiot_qweather_sdk-1.0.1.dist-info/WHEEL
lsyiot_qweather_sdk-1.0.1.dist-info/top_level.txt
lsyiot_qweather_sdk-1.0.1.dist-info/RECORD
