Metadata-Version: 2.4
Name: lsyiot-qweather-sdk
Version: 1.0.1
Summary: 和风天气开发服务Python接口（https://dev.qweather.com）
Home-page: https://github.com/9kl/lsyiot_qweather_sdk
Author: fhp
Author-email: chinafengheping@outlook.com
Classifier: Programming Language :: Python :: 3
Classifier: License :: OSI Approved :: MIT License
Classifier: Operating System :: OS Independent
Requires-Python: >=3.8
License-File: LICENSE
Requires-Dist: requests>=2.25.0
Dynamic: author
Dynamic: author-email
Dynamic: classifier
Dynamic: description
Dynamic: description-content-type
Dynamic: home-page
Dynamic: license-file
Dynamic: requires-dist
Dynamic: requires-python
Dynamic: summary
